{"name":"IDE","slug":"IDE","count":1,"postlist":[{"title":"IDEA使用整理","uid":"b101998dd022ec6c59d67b19a90f6218","slug":"IDEA使用整理","date":"2023-08-18T14:09:53.000Z","updated":"2023-08-18T14:09:53.000Z","comments":true,"path":"api/articles/IDEA使用整理.json","keywords":null,"cover":"/images/idea.jpg","text":"IDEA设置、插件、主题、字体...","link":"","photos":[],"count_time":{"symbolsCount":"1.3k","symbolsTime":"1 mins."},"categories":[{"name":"编程","slug":"编程","count":6,"path":"api/categories/编程.json"}],"tags":[{"name":"IDE","slug":"IDE","count":1,"path":"api/tags/IDE.json"}],"author":{"name":"Dxc","slug":"blog-author","avatar":"/images/avatar.png","link":"/","description":"Free will is not free. <br /> @ <b>公众号：精准拔草</b>","socials":{"github":"","twitter":"","stackoverflow":"","wechat":"","qq":"","weibo":"","zhihu":"","csdn":"","juejin":"","customs":{}}}}]}